{
  "lessonId": "lesson-139-subject",
  "level": "C1",
  "category": "collocations",
  "title": "Subject",
  "points": [
    {
      "type": "explanation",
      "label": "Subject collocations",
      "content": {
        "phrasalVerb": "Subject",
        "definition": "Common collocations with \"subject\"",
        "examples": [
          "Subject sb to — Cause someone to experience something unpleasant",
          "Bringing together the subject — Combining ideas or elements of a topic"
        ]
      }
    }
  ],
  "meta": {
    "word": "subject",
    "entryCount": 2
  }
}
