{"id":"mix_cw23","level":"mix","index":23,"title":"Mix Crossword #24","difficulty":"mixed","generated":"2026-07-21T20:29:33.657Z","rows":19,"cols":20,"grid":[[0,0,0,0,0,0,0,0,0,0,0,0,1,1,1,1,1,0,0,0],[0,0,0,0,1,1,1,1,1,1,0,0,1,0,0,0,0,0,0,0],[0,0,0,0,1,0,0,0,0,0,0,0,1,1,1,1,1,1,0,0],[0,0,0,1,1,1,1,1,1,0,0,0,1,0,0,0,0,0,0,0],[0,1,0,0,1,0,0,0,0,0,0,0,1,0,0,0,0,0,0,1],[0,1,0,0,1,0,1,0,0,0,0,0,1,1,1,1,1,1,1,1],[1,1,1,1,1,1,1,0,1,0,0,0,0,1,0,0,0,0,0,1],[0,1,0,0,0,0,1,0,1,0,0,1,0,1,0,0,0,0,0,1],[0,1,0,1,1,1,1,1,1,1,1,1,1,1,1,0,1,0,0,1],[0,1,0,0,1,0,1,0,1,0,0,1,0,1,0,0,1,0,0,1],[0,1,0,0,1,0,1,0,1,0,0,1,0,1,0,0,1,0,0,1],[0,0,0,0,1,0,1,0,1,0,0,1,0,1,0,0,1,0,0,0],[0,0,0,0,1,0,1,0,1,0,1,1,1,1,1,1,1,1,1,1],[0,0,0,0,1,0,1,0,1,0,0,1,0,1,0,0,1,0,1,0],[0,0,0,0,1,0,0,0,1,0,0,1,0,0,0,0,1,0,1,0],[0,0,0,0,0,1,1,1,1,0,0,1,0,0,0,0,1,0,1,0],[0,0,0,0,0,0,0,0,0,0,0,1,0,0,0,0,1,0,1,0],[0,0,0,0,0,0,0,0,0,0,0,0,0,0,0,0,0,0,1,0],[0,0,0,0,0,0,0,0,0,0,0,0,0,0,0,0,0,0,1,0]],"numberedCells":{"0,12":1,"1,4":2,"2,12":3,"3,3":4,"4,1":5,"4,19":6,"5,6":7,"5,12":8,"5,13":9,"6,0":10,"6,8":11,"7,11":12,"8,3":13,"8,4":14,"8,16":15,"12,10":16,"12,18":17,"15,5":18},"across":[{"number":1,"word":"ASSET","clue":"A useful or valuable skill, quality, or possession.","type":"vocabulary","row":0,"col":12,"length":5},{"number":2,"word":"PILLOW","clue":"A soft cushion for the head.","type":"vocabulary","row":1,"col":4,"length":6},{"number":3,"word":"SOCIAL","clue":"A professional who helps people in need | ___ worker","type":"collocation","row":2,"col":12,"length":6},{"number":4,"word":"ENTIRE","clue":"The whole thing or group.","type":"vocabulary","row":3,"col":3,"length":6},{"number":8,"word":"DICTATOR","clue":"Someone who uses force to take and keep power in a country.","type":"vocabulary","row":5,"col":12,"length":8},{"number":10,"word":"FURTHER","clue":"At or from a greater distance or time.","type":"vocabulary","row":6,"col":0,"length":7},{"number":13,"word":"CONVENTIONAL","clue":"Based on what is generally done or believed.","type":"vocabulary","row":8,"col":3,"length":12},{"number":16,"word":"BIOLOGICAL","clue":"Relating to living things and the processes of life.","type":"vocabulary","row":12,"col":10,"length":10},{"number":18,"word":"FLAT","clue":"Relating to something that is level and smooth with no curved parts.","type":"vocabulary","row":15,"col":5,"length":4}],"down":[{"number":1,"word":"ABSURD","clue":"Extremely silly or unreasonable.","type":"vocabulary","row":0,"col":12,"length":6},{"number":2,"word":"PUNISH","clue":"To make someone suffer for breaking the rules or laws.","type":"vocabulary","row":1,"col":4,"length":6},{"number":5,"word":"COUNTER","clue":"A flat surface in a kitchen or store.","type":"vocabulary","row":4,"col":1,"length":7},{"number":6,"word":"PRODUCT","clue":"Something grown or made in a factory in order to be sold.","type":"vocabulary","row":4,"col":19,"length":7},{"number":7,"word":"PROVISION","clue":"The act of giving something to people in need or want.","type":"vocabulary","row":5,"col":6,"length":9},{"number":9,"word":"INCAPABLE","clue":"Not able to do something.","type":"vocabulary","row":5,"col":13,"length":9},{"number":11,"word":"PUNISHMENT","clue":"Something that one must endure for any wrongdoing.","type":"vocabulary","row":6,"col":8,"length":10},{"number":12,"word":"CONSPIRACY","clue":"A secret plan that two or more people make together to do something harmful or illegal.","type":"vocabulary","row":7,"col":11,"length":10},{"number":14,"word":"OBSCURE","clue":"Not well known.","type":"vocabulary","row":8,"col":4,"length":7},{"number":15,"word":"INTUITION","clue":"An ability to know or understand something through your feelings rather than by considering facts or evidence.","type":"vocabulary","row":8,"col":16,"length":9},{"number":17,"word":"ACQUIRE","clue":"To get or obtain something.","type":"vocabulary","row":12,"col":18,"length":7}]}