{
  "schemaVersion": "sune-english-unit-v2-interactive-formats",
  "course": "B1 English",
  "block": 7,
  "unit": 7,
  "type": "review",
  "unitTitle": "Review 7: Units 19, 20 and 21",
  "unitSubtitle": "Review 7: Units 19, 20 and 21",
  "unitLevel": "B1",
  "unitFocus": [
    "Review 7: Units 19, 20 and 21"
  ],
  "estimatedDurationMinutes": 25,
  "lessonStyle": "sune-play-interactive",
  "migrationMeta": {
    "pilot": false,
    "sourceFile": "data/Course/B1/Review7.json",
    "migratedAt": "2026-07-09",
    "legacyExerciseCount": 5,
    "sourceType": "review"
  },
  "unitStructure": {
    "mode": "practice_only",
    "theoryRequiredBeforePractice": false,
    "allowTheoryReviewFromPractice": false,
    "practiceNodesUseExerciseItemsAsContentBank": true
  },
  "theory": {
    "id": "b1-r7-theory",
    "title": "Review",
    "shortTitle": "Review",
    "displayMode": "swipeable_cards",
    "completionRule": {
      "type": "view_all_cards",
      "required": false
    },
    "cards": []
  },
  "practiceConfig": {
    "formatDefinitions": [
      {
        "formatType": "passage_gap_fill",
        "displayName": "Complete the passage",
        "defaultLives": 5,
        "maxLifeLossPerScreen": 1,
        "attemptsPerScreen": 1,
        "failureAction": "show_explanation_then_continue",
        "interaction": {
          "component": "passage_inline_gaps",
          "studentAction": "type_gap_answers",
          "evaluationTrigger": "check_button",
          "gapInputStyle": "pill"
        }
      },
      {
        "formatType": "free_text_gap_fill",
        "displayName": "Complete the gap",
        "defaultLives": 5,
        "maxLifeLossPerScreen": 1,
        "attemptsPerScreen": 1,
        "failureAction": "show_explanation_then_continue",
        "interaction": {
          "component": "inline_gap_input",
          "studentAction": "type_answer",
          "evaluationTrigger": "check_button"
        }
      },
      {
        "formatType": "mc_4_option",
        "displayName": "Multiple choice",
        "defaultLives": 5,
        "maxLifeLossPerScreen": 1,
        "attemptsPerScreen": 1,
        "failureAction": "show_explanation_then_continue",
        "interaction": {
          "component": "option_cards",
          "studentAction": "tap_one_option",
          "evaluationTrigger": "check_button"
        }
      }
    ],
    "globalRules": {
      "failedItemsReturnToQueue": true,
      "maxRepeatedFailuresBeforeFallback": 2,
      "doNotPenalize": [
        "capitalization_only",
        "extra_spaces",
        "missing_final_period",
        "minor_punctuation"
      ]
    }
  },
  "practiceNodes": [
    {
      "nodeId": "b1-r7-node-1",
      "title": "Review 7: Units 19, 20 and 21",
      "shortTitle": "Review",
      "focus": [
        "passage_gap_fill",
        "free_text_gap_fill",
        "mc_4_option"
      ],
      "lives": 5,
      "passCondition": {
        "minimumCorrectScreens": 25,
        "allowFinishWithZeroLives": false
      },
      "screenGeneration": [
        {
          "sourceExerciseId": "b1-u7-ex-a",
          "formatType": "passage_gap_fill",
          "screenMode": "single_passage_with_gaps"
        },
        {
          "sourceExerciseId": "b1-u7-ex-b",
          "formatType": "free_text_gap_fill",
          "sourceItemIds": [
            "b1-u7-exb-1",
            "b1-u7-exb-2",
            "b1-u7-exb-3",
            "b1-u7-exb-4",
            "b1-u7-exb-5",
            "b1-u7-exb-6",
            "b1-u7-exb-7",
            "b1-u7-exb-8"
          ]
        },
        {
          "sourceExerciseId": "b1-u7-ex-c",
          "formatType": "free_text_gap_fill",
          "sourceItemIds": [
            "b1-u7-exc-1",
            "b1-u7-exc-2",
            "b1-u7-exc-3",
            "b1-u7-exc-4",
            "b1-u7-exc-5"
          ]
        },
        {
          "sourceExerciseId": "b1-u7-ex-d",
          "formatType": "mc_4_option",
          "sourceItemIds": [
            "b1-u7-exd-1",
            "b1-u7-exd-2",
            "b1-u7-exd-3",
            "b1-u7-exd-4",
            "b1-u7-exd-5",
            "b1-u7-exd-6",
            "b1-u7-exd-7",
            "b1-u7-exd-8",
            "b1-u7-exd-9",
            "b1-u7-exd-10"
          ]
        },
        {
          "sourceExerciseId": "b1-u7-ex-e",
          "formatType": "free_text_gap_fill",
          "sourceItemIds": [
            "b1-u7-exe-1",
            "b1-u7-exe-2",
            "b1-u7-exe-3",
            "b1-u7-exe-4",
            "b1-u7-exe-5",
            "b1-u7-exe-6",
            "b1-u7-exe-7",
            "b1-u7-exe-8",
            "b1-u7-exe-9",
            "b1-u7-exe-10",
            "b1-u7-exe-11",
            "b1-u7-exe-12"
          ]
        }
      ]
    }
  ],
  "queueBehaviour": {
    "initialOrder": "pedagogical",
    "shuffleWithinNode": false,
    "failedItemPlacement": "end_of_queue",
    "repeatFailedItemsBeforeCompletion": true,
    "maxScreensPerNode": 36,
    "minimumScreensPerNode": 6
  },
  "xpRules": {
    "baseXpPerCorrectScreen": 10,
    "bonusXpForPerfectNode": 20,
    "bonusXpForNoHints": 10,
    "xpPenaltyPerLifeLost": 2
  },
  "feedbackTone": {
    "correct": [
      "Nice!",
      "Correct!"
    ],
    "incorrect": [
      "Not quite.",
      "Try again."
    ],
    "hintPrompts": []
  },
  "contentBanks": {
    "source": "embedded_exercises",
    "requiredExerciseIds": [
      "b1-u7-ex-a",
      "b1-u7-ex-b",
      "b1-u7-ex-c",
      "b1-u7-ex-d",
      "b1-u7-ex-e"
    ],
    "exercises": [
      {
        "id": "b1-u7-ex-a",
        "type": "exercise",
        "exerciseType": "passage_gap_fill",
        "exerciseTypeName": "A: Word formation",
        "title": "A: Word formation",
        "instructions": "Use the word given in capitals at the end of each line to form a word that fits in the gap in the same line.",
        "studentInstruction": "Use the word given in capitals at the end of each line to form a word that fits in the gap in the same line.",
        "legacyKey": "A",
        "legacyPattern": "passage-input",
        "interaction": {
          "formatType": "passage_gap_fill",
          "sequentialGaps": true,
          "requireWordBankAssignment": false,
          "gapInputStyle": "underline_expand"
        },
        "passage": "Keeping in touch\nGood (1) ...... (COMMUNICATE) is important when people live far apart. A clear (2) ...... (TRANSLATE) can help people understand messages in another language. Sometimes a word or (3) ...... (EXPRESS) sounds natural in one language but strange in another. A good (4) ...... (SPEAK) knows how to make the message sound clear. Online messages can be (5) ...... (PREDICT), so we don't always know when someone will reply. A strong Internet (6) ...... (CONNECT) makes video calls easier. I can say with (7) ...... (CERTAIN) that technology has changed friendships. People can now share (8) ...... (INFORM) instantly, write (9) ...... (SECRET) to each other, and stay in contact with friends all over the world. It has (10) ...... (CERTAIN) made communication faster.",
        "formatType": "passage_gap_fill",
        "answers": [
          "communication",
          "translation",
          "expression",
          "speaker",
          "unpredictable",
          "connection",
          "certainty",
          "information",
          "secretly",
          "certainly"
        ],
        "explanations": [
          "Noun from COMMUNICATE → good **communication**.",
          "Noun from TRANSLATE → a clear **translation**.",
          "Noun from EXPRESS → a word or **expression**.",
          "Person from SPEAK → a good **speaker**.",
          "Adjective from PREDICT → messages can be **unpredictable**.",
          "Noun from CONNECT → Internet **connection**.",
          "Noun from CERTAIN → with **certainty**.",
          "Noun from INFORM → share **information**.",
          "Adverb from SECRET → write **secretly** to each other.",
          "Adverb from CERTAIN → has **certainly** made communication faster."
        ]
      },
      {
        "id": "b1-u7-ex-b",
        "type": "exercise",
        "exerciseType": "free_text_gap_fill",
        "exerciseTypeName": "B: Write one word in each gap",
        "title": "B: Write one word in each gap",
        "instructions": "Write one word in each gap.",
        "studentInstruction": "Write one word in each gap.",
        "legacyKey": "B",
        "legacyPattern": "gap-fill",
        "interaction": {
          "formatType": "free_text_gap_fill"
        },
        "items": [
          {
            "id": "b1-u7-exb-1",
            "formatType": "free_text_gap_fill",
            "sentence": "When does the next issue of that science magazine come ...... ?",
            "answer": "out",
            "acceptedAnswers": [
              "out"
            ],
            "explanation": "Be published → magazine **come out**."
          },
          {
            "id": "b1-u7-exb-2",
            "formatType": "free_text_gap_fill",
            "sentence": "The storm damaged the line and cut the Internet ...... .",
            "answer": "off",
            "acceptedAnswers": [
              "off"
            ],
            "explanation": "Disconnect → cut the Internet **off**."
          },
          {
            "id": "b1-u7-exb-3",
            "formatType": "free_text_gap_fill",
            "sentence": "I'm busy now, but I'll call you ...... after lunch.",
            "answer": "back",
            "acceptedAnswers": [
              "back"
            ],
            "explanation": "Return a call → call you **back**."
          },
          {
            "id": "b1-u7-exb-4",
            "formatType": "free_text_gap_fill",
            "sentence": "He got angry and hung ...... before I could explain.",
            "answer": "up",
            "acceptedAnswers": [
              "up"
            ],
            "explanation": "End a call → hung **up**."
          },
          {
            "id": "b1-u7-exb-5",
            "formatType": "free_text_gap_fill",
            "sentence": "Can you print this booking confirmation ...... for me?",
            "answer": "out",
            "acceptedAnswers": [
              "out"
            ],
            "explanation": "Make a copy → print **out**."
          },
          {
            "id": "b1-u7-exb-6",
            "formatType": "free_text_gap_fill",
            "sentence": "She logged ...... the school website to check her homework.",
            "answer": "onto",
            "acceptedAnswers": [
              "onto"
            ],
            "explanation": "Sign in → logged **onto** the website."
          },
          {
            "id": "b1-u7-exb-7",
            "formatType": "free_text_gap_fill",
            "sentence": "Please fill ...... your name and address clearly.",
            "answer": "in",
            "acceptedAnswers": [
              "in"
            ],
            "explanation": "Complete a form → fill **in** your name."
          },
          {
            "id": "b1-u7-exb-8",
            "formatType": "free_text_gap_fill",
            "sentence": "After checking my messages, I logged ...... and shut down the computer.",
            "answer": "off",
            "acceptedAnswers": [
              "off"
            ],
            "explanation": "Sign out → logged **off**."
          }
        ]
      },
      {
        "id": "b1-u7-ex-c",
        "type": "exercise",
        "exerciseType": "free_text_gap_fill",
        "exerciseTypeName": "C: Key Word Transformation",
        "title": "C: Key Word Transformation",
        "instructions": "Complete each second sentence using the word given, so that it has a similar meaning to the first sentence. Write between two and five words.",
        "studentInstruction": "Complete each second sentence using the word given, so that it has a similar meaning to the first sentence. Write between two and five words.",
        "legacyKey": "C",
        "legacyPattern": "gap-fill",
        "interaction": {
          "formatType": "free_text_gap_fill"
        },
        "items": [
          {
            "id": "b1-u7-exc-1",
            "formatType": "free_text_gap_fill",
            "sentence": "Laura sent me an invitation by e-mail. **received**\nI ...... Laura.",
            "answer": "received an invitation from",
            "acceptedAnswers": [
              "received an invitation from"
            ],
            "explanation": "Passive receive → **received an invitation from** Laura."
          },
          {
            "id": "b1-u7-exc-2",
            "formatType": "free_text_gap_fill",
            "sentence": "It isn't necessary to bring your own headphones. **have**\nYou ...... bring your own headphones.",
            "answer": "don't have to",
            "acceptedAnswers": [
              "don't have to"
            ],
            "explanation": "Not necessary → **don't have to** bring headphones."
          },
          {
            "id": "b1-u7-exc-3",
            "formatType": "free_text_gap_fill",
            "sentence": "Nina is able to speak and understand German. **can**\nNina ...... German.",
            "answer": "can speak and understand",
            "acceptedAnswers": [
              "can speak and understand"
            ],
            "explanation": "Ability → Nina **can speak and understand** German."
          },
          {
            "id": "b1-u7-exc-4",
            "formatType": "free_text_gap_fill",
            "sentence": "It wasn't necessary for us to print the tickets. **need**\nWe ...... to print the tickets.",
            "answer": "didn't need",
            "acceptedAnswers": [
              "didn't need"
            ],
            "explanation": "Not necessary (past) → **didn't need** to print."
          },
          {
            "id": "b1-u7-exc-5",
            "formatType": "free_text_gap_fill",
            "sentence": "It's possible that the message is from our teacher. **might**\nThe message ...... from our teacher.",
            "answer": "might be",
            "acceptedAnswers": [
              "might be"
            ],
            "explanation": "Possibility → message **might be** from our teacher."
          }
        ]
      },
      {
        "id": "b1-u7-ex-d",
        "type": "exercise",
        "exerciseType": "mc_4_option",
        "exerciseTypeName": "D: Choose the correct answer",
        "title": "D: Choose the correct answer",
        "instructions": "Choose the correct answer.",
        "studentInstruction": "Choose the correct answer.",
        "legacyKey": "D",
        "legacyPattern": "mc-standalone",
        "interaction": {
          "formatType": "mc_4_option"
        },
        "items": [
          {
            "id": "b1-u7-exd-1",
            "formatType": "mc_4_option",
            "sentenceBefore": "You",
            "sentenceAfter": "use your phone during the test. It's forbidden.",
            "options": [
              {
                "letter": "A",
                "text": "mustn't"
              },
              {
                "letter": "B",
                "text": "don't have to"
              },
              {
                "letter": "C",
                "text": "shouldn't to"
              },
              {
                "letter": "D",
                "text": "needn't"
              }
            ],
            "answer": "A",
            "explanationContent": {
              "whyCorrect": "The context points to \"mustn't\" — forbidden during test.",
              "wrongOptions": {
                "B": "\"don't have to\" does not match the grammar or meaning clue in this sentence — \"mustn't\" is correct.",
                "don't have to": "\"don't have to\" does not match the grammar or meaning clue in this sentence — \"mustn't\" is correct.",
                "C": "\"shouldn't to\" does not match the grammar or meaning clue in this sentence — \"mustn't\" is correct.",
                "shouldn't to": "\"shouldn't to\" does not match the grammar or meaning clue in this sentence — \"mustn't\" is correct.",
                "D": "\"needn't\" does not match the grammar or meaning clue in this sentence — \"mustn't\" is correct.",
                "needn't": "\"needn't\" does not match the grammar or meaning clue in this sentence — \"mustn't\" is correct."
              },
              "usefulTip": "Eliminate options that break grammar first, then check which remaining word fits the meaning.",
              "grammarFocus": "Possessive forms and possessive determiners show who something belongs to."
            }
          },
          {
            "id": "b1-u7-exd-2",
            "formatType": "mc_4_option",
            "sentenceBefore": "I",
            "sentenceAfter": "ride a horse when I was younger.",
            "options": [
              {
                "letter": "A",
                "text": "could"
              },
              {
                "letter": "B",
                "text": "was able to"
              },
              {
                "letter": "C",
                "text": "might"
              },
              {
                "letter": "D",
                "text": "should"
              }
            ],
            "answer": "A",
            "explanationContent": {
              "whyCorrect": "The context points to \"could\" — past ability.",
              "wrongOptions": {
                "B": "\"was able to\" does not match the grammar or meaning clue in this sentence — \"could\" is correct.",
                "was able to": "\"was able to\" does not match the grammar or meaning clue in this sentence — \"could\" is correct.",
                "C": "\"might\" does not match the grammar or meaning clue in this sentence — \"could\" is correct.",
                "might": "\"might\" does not match the grammar or meaning clue in this sentence — \"could\" is correct.",
                "D": "\"should\" does not match the grammar or meaning clue in this sentence — \"could\" is correct.",
                "should": "\"should\" does not match the grammar or meaning clue in this sentence — \"could\" is correct."
              },
              "usefulTip": "Eliminate options that break grammar first, then check which remaining word fits the meaning.",
              "vocabularyFocus": "\"could\" is the only option that matches both meaning and register in this sentence."
            }
          },
          {
            "id": "b1-u7-exd-3",
            "formatType": "mc_4_option",
            "sentenceBefore": "You",
            "sentenceAfter": "buy a ticket today – entrance is free.",
            "options": [
              {
                "letter": "A",
                "text": "mustn't"
              },
              {
                "letter": "B",
                "text": "can't"
              },
              {
                "letter": "C",
                "text": "don't have to"
              },
              {
                "letter": "D",
                "text": "aren't allowed to"
              }
            ],
            "answer": "C",
            "explanationContent": {
              "whyCorrect": "The context points to \"don't have to\" — free entrance.",
              "wrongOptions": {
                "A": "\"mustn't\" does not match the grammar or meaning clue in this sentence — \"don't have to\" is correct.",
                "mustn't": "\"mustn't\" does not match the grammar or meaning clue in this sentence — \"don't have to\" is correct.",
                "B": "\"can't\" does not match the grammar or meaning clue in this sentence — \"don't have to\" is correct.",
                "can't": "\"can't\" does not match the grammar or meaning clue in this sentence — \"don't have to\" is correct.",
                "D": "\"aren't allowed to\" does not match the grammar or meaning clue in this sentence — \"don't have to\" is correct.",
                "aren't allowed to": "\"aren't allowed to\" does not match the grammar or meaning clue in this sentence — \"don't have to\" is correct."
              },
              "usefulTip": "Eliminate options that break grammar first, then check which remaining word fits the meaning.",
              "vocabularyFocus": "\"don't have to\" is the only option that matches both meaning and register in this sentence."
            }
          },
          {
            "id": "b1-u7-exd-4",
            "formatType": "mc_4_option",
            "sentenceBefore": "He",
            "sentenceAfter": "be in his room – I can hear music upstairs.",
            "options": [
              {
                "letter": "A",
                "text": "must"
              },
              {
                "letter": "B",
                "text": "should"
              },
              {
                "letter": "C",
                "text": "might"
              },
              {
                "letter": "D",
                "text": "has to"
              }
            ],
            "answer": "A",
            "explanationContent": {
              "whyCorrect": "The context points to \"must\" — music upstairs.",
              "wrongOptions": {
                "B": "\"should\" does not match the grammar or meaning clue in this sentence — \"must\" is correct.",
                "should": "\"should\" does not match the grammar or meaning clue in this sentence — \"must\" is correct.",
                "C": "\"might\" does not match the grammar or meaning clue in this sentence — \"must\" is correct.",
                "might": "\"might\" does not match the grammar or meaning clue in this sentence — \"must\" is correct.",
                "D": "\"has to\" does not match the grammar or meaning clue in this sentence — \"must\" is correct.",
                "has to": "\"has to\" does not match the grammar or meaning clue in this sentence — \"must\" is correct."
              },
              "usefulTip": "Eliminate options that break grammar first, then check which remaining word fits the meaning.",
              "vocabularyFocus": "\"must\" is the only option that matches both meaning and register in this sentence."
            }
          },
          {
            "id": "b1-u7-exd-5",
            "formatType": "mc_4_option",
            "sentenceBefore": "",
            "sentenceAfter": "I use your charger for a few minutes?",
            "options": [
              {
                "letter": "A",
                "text": "Should"
              },
              {
                "letter": "B",
                "text": "Must"
              },
              {
                "letter": "C",
                "text": "May"
              },
              {
                "letter": "D",
                "text": "Ought"
              }
            ],
            "answer": "C",
            "explanationContent": {
              "whyCorrect": "The context points to \"May\" — permission request.",
              "wrongOptions": {
                "A": "\"Should\" does not match the grammar or meaning clue in this sentence — \"May\" is correct.",
                "Should": "\"Should\" does not match the grammar or meaning clue in this sentence — \"May\" is correct.",
                "B": "\"Must\" does not match the grammar or meaning clue in this sentence — \"May\" is correct.",
                "Must": "\"Must\" does not match the grammar or meaning clue in this sentence — \"May\" is correct.",
                "D": "\"Ought\" does not match the grammar or meaning clue in this sentence — \"May\" is correct.",
                "Ought": "\"Ought\" does not match the grammar or meaning clue in this sentence — \"May\" is correct."
              },
              "usefulTip": "Time expressions like for, since, already, and yet are strong present-perfect signals.",
              "vocabularyFocus": "\"May\" is the only option that matches both meaning and register in this sentence."
            }
          },
          {
            "id": "b1-u7-exd-6",
            "formatType": "mc_4_option",
            "sentenceBefore": "Cyclists",
            "sentenceAfter": "stop at red lights. It's the law.",
            "options": [
              {
                "letter": "A",
                "text": "should"
              },
              {
                "letter": "B",
                "text": "must"
              },
              {
                "letter": "C",
                "text": "may"
              },
              {
                "letter": "D",
                "text": "could"
              }
            ],
            "answer": "B",
            "explanationContent": {
              "whyCorrect": "The context points to \"must\" — law.",
              "wrongOptions": {
                "A": "\"should\" does not match the grammar or meaning clue in this sentence — \"must\" is correct.",
                "should": "\"should\" does not match the grammar or meaning clue in this sentence — \"must\" is correct.",
                "C": "\"may\" does not match the grammar or meaning clue in this sentence — \"must\" is correct.",
                "may": "\"may\" does not match the grammar or meaning clue in this sentence — \"must\" is correct.",
                "D": "\"could\" does not match the grammar or meaning clue in this sentence — \"must\" is correct.",
                "could": "\"could\" does not match the grammar or meaning clue in this sentence — \"must\" is correct."
              },
              "usefulTip": "Eliminate options that break grammar first, then check which remaining word fits the meaning.",
              "grammarFocus": "Possessive forms and possessive determiners show who something belongs to."
            }
          },
          {
            "id": "b1-u7-exd-7",
            "formatType": "mc_4_option",
            "sentenceBefore": "She",
            "sentenceAfter": "be hungry. She hasn't eaten all day.",
            "options": [
              {
                "letter": "A",
                "text": "can't"
              },
              {
                "letter": "B",
                "text": "mustn't"
              },
              {
                "letter": "C",
                "text": "must"
              },
              {
                "letter": "D",
                "text": "should"
              }
            ],
            "answer": "C",
            "explanationContent": {
              "whyCorrect": "The context points to \"must\" — hasn't eaten.",
              "wrongOptions": {
                "A": "\"can't\" does not match the grammar or meaning clue in this sentence — \"must\" is correct.",
                "can't": "\"can't\" does not match the grammar or meaning clue in this sentence — \"must\" is correct.",
                "B": "\"mustn't\" does not match the grammar or meaning clue in this sentence — \"must\" is correct.",
                "mustn't": "\"mustn't\" does not match the grammar or meaning clue in this sentence — \"must\" is correct.",
                "D": "\"should\" does not match the grammar or meaning clue in this sentence — \"must\" is correct.",
                "should": "\"should\" does not match the grammar or meaning clue in this sentence — \"must\" is correct."
              },
              "usefulTip": "Eliminate options that break grammar first, then check which remaining word fits the meaning.",
              "vocabularyFocus": "\"must\" is the only option that matches both meaning and register in this sentence."
            }
          },
          {
            "id": "b1-u7-exd-8",
            "formatType": "mc_4_option",
            "sentenceBefore": "You",
            "sentenceAfter": "to check your spelling before sending the e-mail.",
            "options": [
              {
                "letter": "A",
                "text": "ought"
              },
              {
                "letter": "B",
                "text": "must"
              },
              {
                "letter": "C",
                "text": "can"
              },
              {
                "letter": "D",
                "text": "may"
              }
            ],
            "answer": "A",
            "explanationContent": {
              "whyCorrect": "The context points to \"ought\" — advice.",
              "wrongOptions": {
                "B": "\"must\" does not match the grammar or meaning clue in this sentence — \"ought\" is correct.",
                "must": "\"must\" does not match the grammar or meaning clue in this sentence — \"ought\" is correct.",
                "C": "\"can\" does not match the grammar or meaning clue in this sentence — \"ought\" is correct.",
                "can": "\"can\" does not match the grammar or meaning clue in this sentence — \"ought\" is correct.",
                "D": "\"may\" does not match the grammar or meaning clue in this sentence — \"ought\" is correct.",
                "may": "\"may\" does not match the grammar or meaning clue in this sentence — \"ought\" is correct."
              },
              "usefulTip": "Eliminate options that break grammar first, then check which remaining word fits the meaning.",
              "vocabularyFocus": "\"ought\" is the only option that matches both meaning and register in this sentence."
            }
          },
          {
            "id": "b1-u7-exd-9",
            "formatType": "mc_4_option",
            "sentenceBefore": "I",
            "sentenceAfter": "translate that message for you if you like.",
            "options": [
              {
                "letter": "A",
                "text": "can"
              },
              {
                "letter": "B",
                "text": "must"
              },
              {
                "letter": "C",
                "text": "should"
              },
              {
                "letter": "D",
                "text": "ought"
              }
            ],
            "answer": "A",
            "explanationContent": {
              "whyCorrect": "The context points to \"can\" — offer to help.",
              "wrongOptions": {
                "B": "\"must\" does not match the grammar or meaning clue in this sentence — \"can\" is correct.",
                "must": "\"must\" does not match the grammar or meaning clue in this sentence — \"can\" is correct.",
                "C": "\"should\" does not match the grammar or meaning clue in this sentence — \"can\" is correct.",
                "should": "\"should\" does not match the grammar or meaning clue in this sentence — \"can\" is correct.",
                "D": "\"ought\" does not match the grammar or meaning clue in this sentence — \"can\" is correct.",
                "ought": "\"ought\" does not match the grammar or meaning clue in this sentence — \"can\" is correct."
              },
              "usefulTip": "Time expressions like for, since, already, and yet are strong present-perfect signals.",
              "vocabularyFocus": "\"can\" is the only option that matches both meaning and register in this sentence."
            }
          },
          {
            "id": "b1-u7-exd-10",
            "formatType": "mc_4_option",
            "sentenceBefore": "You",
            "sentenceAfter": "send angry messages when you're upset.",
            "options": [
              {
                "letter": "A",
                "text": "mustn't"
              },
              {
                "letter": "B",
                "text": "don't have to"
              },
              {
                "letter": "C",
                "text": "shouldn't"
              },
              {
                "letter": "D",
                "text": "needn't to"
              }
            ],
            "answer": "C",
            "explanationContent": {
              "whyCorrect": "The context points to \"shouldn't\" — bad idea.",
              "wrongOptions": {
                "A": "\"mustn't\" does not match the grammar or meaning clue in this sentence — \"shouldn't\" is correct.",
                "mustn't": "\"mustn't\" does not match the grammar or meaning clue in this sentence — \"shouldn't\" is correct.",
                "B": "\"don't have to\" does not match the grammar or meaning clue in this sentence — \"shouldn't\" is correct.",
                "don't have to": "\"don't have to\" does not match the grammar or meaning clue in this sentence — \"shouldn't\" is correct.",
                "D": "\"needn't to\" does not match the grammar or meaning clue in this sentence — \"shouldn't\" is correct.",
                "needn't to": "\"needn't to\" does not match the grammar or meaning clue in this sentence — \"shouldn't\" is correct."
              },
              "usefulTip": "Eliminate options that break grammar first, then check which remaining word fits the meaning.",
              "vocabularyFocus": "\"shouldn't\" is the only option that matches both meaning and register in this sentence."
            }
          }
        ]
      },
      {
        "id": "b1-u7-ex-e",
        "type": "exercise",
        "exerciseType": "free_text_gap_fill",
        "exerciseTypeName": "E: Complete the sentences",
        "title": "E: Complete the sentences",
        "instructions": "Write one word in each gap.",
        "studentInstruction": "Write one word in each gap.",
        "legacyKey": "E",
        "legacyPattern": "gap-fill",
        "interaction": {
          "formatType": "free_text_gap_fill"
        },
        "items": [
          {
            "id": "b1-u7-exe-1",
            "formatType": "free_text_gap_fill",
            "sentence": "I need to ...... a message to the club secretary.",
            "answer": "send",
            "acceptedAnswers": [
              "send"
            ],
            "explanation": "Send a message → **send** a message."
          },
          {
            "id": "b1-u7-exe-2",
            "formatType": "free_text_gap_fill",
            "sentence": "She ...... the envelope carefully before posting the letter.",
            "answer": "sealed",
            "acceptedAnswers": [
              "sealed"
            ],
            "explanation": "Close an envelope → **sealed** the envelope."
          },
          {
            "id": "b1-u7-exe-3",
            "formatType": "free_text_gap_fill",
            "sentence": "Could you ...... this parcel to the front desk?",
            "answer": "take",
            "acceptedAnswers": [
              "take"
            ],
            "explanation": "Carry → **take** this parcel."
          },
          {
            "id": "b1-u7-exe-4",
            "formatType": "free_text_gap_fill",
            "sentence": "I ...... him a voice message, but he hasn't listened to it yet.",
            "answer": "sent",
            "acceptedAnswers": [
              "sent"
            ],
            "explanation": "Past of send → **sent** him a voice message."
          },
          {
            "id": "b1-u7-exe-5",
            "formatType": "free_text_gap_fill",
            "sentence": "The package was ...... two days late.",
            "answer": "delivered",
            "acceptedAnswers": [
              "delivered"
            ],
            "explanation": "Past passive → package was **delivered** late."
          },
          {
            "id": "b1-u7-exe-6",
            "formatType": "free_text_gap_fill",
            "sentence": "He ...... a quick text to say he had arrived safely.",
            "answer": "sent",
            "acceptedAnswers": [
              "sent"
            ],
            "explanation": "Past of send → **sent** a quick text."
          },
          {
            "id": "b1-u7-exe-7",
            "formatType": "free_text_gap_fill",
            "sentence": "She printed ...... the form and signed it.",
            "answer": "out",
            "acceptedAnswers": [
              "out"
            ],
            "explanation": "Make a copy → printed **out** the form."
          },
          {
            "id": "b1-u7-exe-8",
            "formatType": "free_text_gap_fill",
            "sentence": "I've been trying to ...... in touch with my old classmate.",
            "answer": "get",
            "acceptedAnswers": [
              "get"
            ],
            "explanation": "Stay in contact → **get** in touch with."
          },
          {
            "id": "b1-u7-exe-9",
            "formatType": "free_text_gap_fill",
            "sentence": "You must ...... in this application form before Friday.",
            "answer": "fill",
            "acceptedAnswers": [
              "fill"
            ],
            "explanation": "Complete a form → **fill** in this application."
          },
          {
            "id": "b1-u7-exe-10",
            "formatType": "free_text_gap_fill",
            "sentence": "The reception desk is ...... a package for you.",
            "answer": "holding",
            "acceptedAnswers": [
              "holding"
            ],
            "explanation": "Keeping for you → **holding** a package."
          },
          {
            "id": "b1-u7-exe-11",
            "formatType": "free_text_gap_fill",
            "sentence": "He wrote the address on the ...... and posted the letter.",
            "answer": "envelope",
            "acceptedAnswers": [
              "envelope"
            ],
            "explanation": "Letter container → address on the **envelope**."
          },
          {
            "id": "b1-u7-exe-12",
            "formatType": "free_text_gap_fill",
            "sentence": "She forwarded the announcement to all her ...... .",
            "answer": "colleagues",
            "acceptedAnswers": [
              "colleagues"
            ],
            "explanation": "Work colleagues → forwarded to all her **colleagues**."
          }
        ]
      }
    ]
  }
}
