{
  "block": 6,
  "unit": 12,
  "type": "vocabulary",
  "unitTitle": "Unit 12: The law and crime",
  "sections": {
    "topic_vocabulary": {
      "vocabulary": [
        {
          "word": "proof / evidence"
        },
        {
          "word": "rule / law / justice / right"
        },
        {
          "word": "vandal / hooligan"
        },
        {
          "word": "suspect / arrest / charge"
        },
        {
          "word": "judge / jury"
        },
        {
          "word": "sentence / imprison"
        },
        {
          "word": "suspect / accused"
        },
        {
          "word": "prosecute / persecute"
        },
        {
          "word": "innocent / guilty"
        },
        {
          "word": "decision / verdict"
        },
        {
          "word": "capital punishment / corporal punishment"
        },
        {
          "word": "witness / bystander"
        },
        {
          "word": "commit / break"
        },
        {
          "word": "robber / burglar / thief"
        },
        {
          "word": "lawyer / solicitor"
        }
      ]
    },
    "phrasal_verbs": [
      {
        "verb": "back down",
        "meaning": "stop demanding sth, stop saying that you will do sth"
      },
      {
        "verb": "hand in",
        "meaning": "give to a person in authority"
      },
      {
        "verb": "break out",
        "meaning": "escape (from prison)"
      },
      {
        "verb": "hold up",
        "meaning": "rob while threatening violence; delay"
      },
      {
        "verb": "bring in",
        "meaning": "introduce a new law or system"
      },
      {
        "verb": "let off",
        "meaning": "give little or no punishment; make a bomb, etc explode"
      },
      {
        "verb": "chase after",
        "meaning": "follow sb/sth quickly in order to catch them"
      },
      {
        "verb": "look into",
        "meaning": "investigate"
      },
      {
        "verb": "come forward",
        "meaning": "offer help or information"
      },
      {
        "verb": "make off",
        "meaning": "escape"
      },
      {
        "verb": "get away with",
        "meaning": "escape punishment for"
      },
      {
        "verb": "take down",
        "meaning": "write down what someone says"
      },
      {
        "verb": "go off",
        "meaning": "explode; be fired (for a gun, usually accidentally)"
      },
      {
        "verb": "take in",
        "meaning": "trick sb into believing sth that is not true"
      }
    ],
    "collocations_patterns": {
      "account": [
        "on account of",
        "take into account",
        "account for sth"
      ],
      "advantage": [
        "take advantage of sth/sb",
        "have an advantage over sth/sb",
        "at an advantage",
        "an/one/etc advantage (of sth)"
      ],
      "blame": [
        "be to blame (for sth/doing)",
        "get/take the blame (for sth/doing)",
        "put the blame on sth/sb",
        "blame sth (on sb)",
        "blame sb for sth/doing"
      ],
      "damage": [
        "do/cause damage (to sth)"
      ],
      "fault": [
        "at fault",
        "find fault with sth/sb"
      ],
      "intention": [
        "have the/no intention of doing"
      ],
      "mistake": [
        "make a mistake",
        "a mistake (to do)",
        "mistake sb for sb",
        "do sth by mistake"
      ],
      "necessary": [
        "necessary (for sb) to do"
      ],
      "order": [
        "in order",
        "put sth in order",
        "in order to do",
        "give an order (to sb) (to do)"
      ],
      "permission": [
        "give sb permission to do",
        "ask (sb) for permission to do",
        "have/ask for/get permission (from sb) to do"
      ],
      "purpose": [
        "do sth on purpose",
        "purpose of sth"
      ],
      "reason": [
        "reason why",
        "reason for sth",
        "reason with sb"
      ],
      "solution": [
        "have/find/think of/work out/come up with/figure out a solution (to sth)"
      ],
      "wrong": [
        "do wrong",
        "do the wrong thing",
        "the wrong thing to do",
        "go wrong",
        "the wrong way up"
      ],
      "accuse": [
        "sb of sth/doing"
      ],
      "doubt": [
        "sth",
        "that",
        "if/whether"
      ],
      "make": [
        "sb do",
        "be made to do"
      ],
      "arrest": [
        "sb for sth/doing"
      ],
      "forgive": [
        "sb for sth/doing"
      ],
      "refuse": [
        "to do sth",
        "sth"
      ],
      "charge": [
        "sb with sth"
      ],
      "glimpse": [
        "sth",
        "catch a glimpse of sth"
      ],
      "respect": [
        "sth",
        "sb for sth/doing",
        "have respect for sth/sb"
      ],
      "claim": [
        "to be/do",
        "that"
      ],
      "guilty": [
        "of sth/doing"
      ],
      "threaten": [
        "to do, threaten sb with sth"
      ],
      "deny": [
        "sth/doing"
      ],
      "legal": [
        "(for sb) to do"
      ]
    },
    "word_formation": [
      {
        "base": "accuse",
        "derivatives": [
          "accused",
          "accusation"
        ]
      },
      {
        "base": "honest",
        "derivatives": [
          "dishonest",
          "(dis)honesty",
          "(dis)honestly"
        ]
      },
      {
        "base": "prison",
        "derivatives": [
          "prisoner",
          "imprisonment(ed)",
          "imprisonment"
        ]
      },
      {
        "base": "addict",
        "derivatives": [
          "addicted",
          "addictive",
          "addiction"
        ]
      },
      {
        "base": "investigate",
        "derivatives": [
          "investigative",
          "investigation",
          "investigator"
        ]
      },
      {
        "base": "prove",
        "derivatives": [
          "proof",
          "(un)proven",
          "disprove"
        ]
      },
      {
        "base": "convict",
        "derivatives": [
          "convicted",
          "conviction"
        ]
      },
      {
        "base": "law",
        "derivatives": [
          "lawyer",
          "(un)lawful"
        ]
      },
      {
        "base": "rob",
        "derivatives": [
          "robbery",
          "robber"
        ]
      },
      {
        "base": "crime",
        "derivatives": [
          "criminal"
        ]
      },
      {
        "base": "murder",
        "derivatives": [
          "murderer"
        ]
      },
      {
        "base": "secure",
        "derivatives": [
          "insecure",
          "(in)security"
        ]
      },
      {
        "base": "evident",
        "derivatives": [
          "evidence",
          "evidently"
        ]
      },
      {
        "base": "offence",
        "derivatives": [
          "offensive",
          "offend",
          "offender"
        ]
      },
      {
        "base": "theft",
        "derivatives": [
          "thief"
        ]
      },
      {
        "base": "forge",
        "derivatives": [
          "forgery",
          "forger"
        ]
      }
    ],
    "exercises": {
      "A": {
        "title": "Topic vocabulary in contrast",
        "instructions": "Complete using the correct form of the words in the box.",
        "questions": [
          {
            "sentence": "All twelve members of the ...... listened carefully to the defence lawyer's closing argument.",
            "answer": "jury"
          },
          {
            "sentence": "Most people can't imagine why anyone would ...... such a violent crime.",
            "answer": "commit"
          },
          {
            "sentence": "The new head teacher said the school ...... would be strictly enforced from the beginning of term.",
            "answer": "rules"
          },
          {
            "sentence": "The prosecution called a forensic scientist as their key ...... on the second day of the trial.",
            "answer": "witness"
          },
          {
            "sentence": "Many countries have banned ...... punishment in schools, arguing that it causes psychological harm.",
            "answer": "corporal"
          },
          {
            "sentence": "Citizens in a democracy have the ...... to protest peacefully against government policies.",
            "answer": "right"
          },
          {
            "sentence": "Those who ...... the rules of the road put other drivers and pedestrians at serious risk.",
            "answer": "break"
          },
          {
            "sentence": "Some politicians argue that existing ...... need to be updated to deal with online crime.",
            "answer": "laws"
          },
          {
            "sentence": "The defendant had already been ...... twice before for similar offences.",
            "answer": "imprisoned"
          },
          {
            "sentence": "The family of the victim stated that ...... had finally been served after many years of waiting.",
            "answer": "justice"
          },
          {
            "sentence": "A number of countries still use ...... punishment, despite growing international opposition.",
            "answer": "capital"
          },
          {
            "sentence": "After a three-week trial, the defendant was ...... to eight years in prison.",
            "answer": "sentenced"
          },
          {
            "sentence": "Several ...... captured the incident on their mobile phones and shared it online.",
            "answer": "bystanders"
          },
          {
            "sentence": "The ...... reminded the jury that they must reach their verdict based solely on the evidence.",
            "answer": "judge"
          }
        ],
        "words": [
          "jury",
          "commit",
          "rules",
          "witness",
          "corporal",
          "right",
          "break",
          "laws",
          "imprisoned",
          "justice",
          "capital",
          "sentenced",
          "bystanders",
          "judge"
        ]
      },
      "B": {
        "type": "crossword",
        "title": "Crossword",
        "instructions": "Solve the crossword using the clues below.",
        "across": [
          {
            "num": 2,
            "clue": "A person who causes disturbance and trouble in public, especially at sports events. (8)",
            "answer": "hooligan"
          },
          {
            "num": 4,
            "clue": "The formal decision reached by a judge or jury at the end of a trial. (7)",
            "answer": "verdict"
          },
          {
            "num": 8,
            "clue": "Someone who takes things belonging to others without permission. (5)",
            "answer": "thief"
          },
          {
            "num": 10,
            "clue": "Information or objects used in a court of law to help prove whether something is true. (8)",
            "answer": "evidence"
          },
          {
            "num": 11,
            "clue": "A person who the police believe may be responsible for a crime. (7)",
            "answer": "suspect"
          },
          {
            "num": 12,
            "clue": "The jury found her not ... of the charges against her. (6)",
            "answer": "guilty"
          },
          {
            "num": 13,
            "clue": "To officially accuse someone of a crime and take legal action against them in court. (9)",
            "answer": "prosecute"
          }
        ],
        "down": [
          {
            "num": 1,
            "clue": "A professional who is qualified to advise on legal matters and represent people in court. (6)",
            "answer": "lawyer"
          },
          {
            "num": 3,
            "clue": "To take someone into police custody when you believe they have committed a crime. (6)",
            "answer": "arrest"
          },
          {
            "num": 4,
            "clue": "A person who deliberately damages or destroys public or private property. (6)",
            "answer": "vandal"
          },
          {
            "num": 5,
            "clue": "If you are not guilty of a crime, you are described as this. (8)",
            "answer": "innocent"
          },
          {
            "num": 6,
            "clue": "To formally accuse someone of committing a crime so they must appear in court. (6)",
            "answer": "charge"
          },
          {
            "num": 7,
            "clue": "To treat a person or group cruelly and unfairly, often because of their beliefs or identity. (9)",
            "answer": "persecute"
          },
          {
            "num": 9,
            "clue": "The person who is on trial in a court of law, also known as the defendant. (7)",
            "answer": "accused"
          }
        ]
      },
      "C": {
        "title": "Phrasal verbs (gap fill)",
        "instructions": "Complete using the correct form of the phrasal verbs in the box.",
        "questions": [
          {
            "sentence": "Members of the public who witnessed the accident were asked to ...... and give their accounts to investigators.",
            "answer": "come forward"
          },
          {
            "sentence": "The two suspects ...... through a back alley before the police arrived.",
            "answer": "made off/went off"
          },
          {
            "sentence": "Inspectors are ...... reports of unsafe working conditions at the factory.",
            "answer": "looking into"
          },
          {
            "sentence": "The council is ...... a new policy to tackle antisocial behaviour in the town centre.",
            "answer": "bringing in"
          },
          {
            "sentence": "A masked man ...... the post office and demanded all the cash in the till.",
            "answer": "held up"
          },
          {
            "sentence": "Two high-risk prisoners ...... of the detention centre by hiding in a delivery van.",
            "answer": "broke out"
          },
          {
            "sentence": "The security guard ...... the shoplifter, eventually catching him at the car park exit.",
            "answer": "chased after"
          },
          {
            "sentence": "Fortunately, the fire alarm ...... just in time for everyone to evacuate the building safely.",
            "answer": "went off"
          }
        ],
        "words": [
          "come forward",
          "made/went off",
          "looking into",
          "bringing in",
          "held up",
          "broke out",
          "chased after",
          "went off"
        ]
      },
      "D": {
        "title": "Phrasal verbs (gap fill)",
        "instructions": "Write one word in each gap.",
        "passageTitle": "The mix-up",
        "passage": "The strangest thing happened to me this morning. I was leaving the gym when I noticed a sports bag near the exit that looked exactly like mine. I picked it up without checking and was heading out to (1) ...... it in at reception, just to make sure, when a gym instructor ran up and told me I was stealing. I tried to explain the situation but she wouldn't (2) ...... down. 'I won't let you get (3) ...... with this,' she said. 'CCTV is everywhere and you'll be caught.' She blocked my path and started to take (4) ...... my name and membership number. I begged her to (5) ...... me off and explained I'd simply made a mistake. Suddenly my cousin Elena and a TV presenter burst through the doors laughing. The whole gym had been in on it, and I'd been completely (6) ...... in!",
        "questions": [
          {
            "sentence": "(1)",
            "answer": "hand"
          },
          {
            "sentence": "(2)",
            "answer": "back"
          },
          {
            "sentence": "(3)",
            "answer": "away"
          },
          {
            "sentence": "(4)",
            "answer": "down"
          },
          {
            "sentence": "(5)",
            "answer": "let"
          },
          {
            "sentence": "(6)",
            "answer": "taken"
          }
        ]
      },
      "E": {
        "title": "Circle the correct word",
        "instructions": "Circle the correct word.",
        "questions": [
          {
            "sentence": "I don't know why you keep **putting / taking** the blame on your teammates.",
            "answer": "taking"
          },
          {
            "sentence": "My dad has no **intention / purpose** of giving up his morning run, no matter how cold it is.",
            "answer": "intention"
          },
          {
            "sentence": "It **doesn't / isn't** necessary to book a table at that café – they always have space.",
            "answer": "isn't"
          },
          {
            "sentence": "The manager **made / gave** us permission to leave early and attend the concert.",
            "answer": "gave"
          },
          {
            "sentence": "We don't know who was at **fault / damage** for the mix-up, but it needs to be resolved.",
            "answer": "fault"
          },
          {
            "sentence": "Sorry, I mistook her **for / with** someone I went to school with.",
            "answer": "for"
          },
          {
            "sentence": "Should coaches take a player's age into **reason / account** when planning their training schedule?",
            "answer": "account"
          },
          {
            "sentence": "Everything **went / had** wrong when the navigation app crashed in the middle of the drive.",
            "answer": "went"
          },
          {
            "sentence": "We need clear traffic signs in **solution / order** to keep the roads safe for everyone.",
            "answer": "order"
          },
          {
            "sentence": "A number of tourists are **making / taking** advantage of the new discount scheme.",
            "answer": "taking"
          }
        ]
      },
      "F": {
        "title": "Matching (Word patterns)",
        "instructions": "Match to make sentences.",
        "questions": [
          {
            "sentence": "They accused me **I** of damaging the car.",
            "answer": "I"
          },
          {
            "sentence": "The cyclist was arrested **A** for running a red light.",
            "answer": "A"
          },
          {
            "sentence": "Three people have been charged **H** with vandalism.",
            "answer": "H"
          },
          {
            "sentence": "The student denied **E** cheating in the exam.",
            "answer": "E"
          },
          {
            "sentence": "I doubt whether **B** the witness is reliable.",
            "answer": "B"
          },
          {
            "sentence": "I caught a glimpse **D** of someone breaking into the building.",
            "answer": "D"
          },
          {
            "sentence": "Peer pressure made me **G** join in with the bullying.",
            "answer": "G"
          },
          {
            "sentence": "She says she was made **F** to hand over her wallet.",
            "answer": "F"
          },
          {
            "sentence": "It is illegal for **C** anyone to drive without a valid licence.",
            "answer": "C"
          }
        ],
        "type": "matching"
      },
      "G": {
        "title": "Cloze (Word patterns)",
        "instructions": "Write one word in each gap.",
        "passageTitle": "A question of trust",
        "passage": "Marco Bianchi used to be my hero. One of the most celebrated chefs of his generation, Marco made us believe that great food could also be ethical. I had so much respect (1) ...... him, particularly because of his 'farm to table' philosophy and his vocal campaign for sustainable sourcing. And now there's no doubt that all the time Bianchi was claiming (2) ...... his ingredients were locally grown, he was importing cheap produce from overseas. Last month, a food standards investigation found Bianchi guilty (3) ...... misleading consumers on a large scale. Bianchi has been banned from using certain quality labels for the next three years, and the agency is threatening (4) ...... take similar cases to court in future. I hope they do. I refuse (5) ...... accept that we should feel sympathy for Bianchi at a time like this. We should never forgive people like Marco Bianchi (6) ...... abusing the trust of their customers.",
        "questions": [
          {
            "sentence": "(1)",
            "answer": "for"
          },
          {
            "sentence": "(2)",
            "answer": "that"
          },
          {
            "sentence": "(3)",
            "answer": "of"
          },
          {
            "sentence": "(4)",
            "answer": "to"
          },
          {
            "sentence": "(5)",
            "answer": "to"
          },
          {
            "sentence": "(6)",
            "answer": "for"
          }
        ]
      },
      "H": {
        "title": "Word formation (error correction)",
        "instructions": "Each sentence contains an error. The incorrect word is shown in bold. Write the correct form on the line.",
        "questions": [
          {
            "sentence": "Many people question whether sending young ...... (offence) to a detention centre actually reduces future crime.",
            "answer": "offenders"
          },
          {
            "sentence": "The defence insisted there was absolutely no solid ...... (prove) that their client had even been in the building.",
            "answer": "proof"
          },
          {
            "sentence": "'I won't answer any more questions until I've been able to speak to my ...... (law),' the man said firmly.",
            "answer": "lawyer"
          },
          {
            "sentence": "You really shouldn't make such serious ...... (accuse) unless you have something concrete to support them.",
            "answer": "accusations"
          },
          {
            "sentence": "After retiring from the force, she spent several years working as a private ...... (investigate).",
            "answer": "investigator"
          },
          {
            "sentence": "'I hope that your period of ...... (prison) has given you time to reflect on your actions,' the judge said.",
            "answer": "imprisonment"
          },
          {
            "sentence": "Due to the nature of the offences, she was moved to a maximum ...... (secure) facility.",
            "answer": "security"
          },
          {
            "sentence": "Deception and ...... (honest) are at the heart of many white-collar crimes.",
            "answer": "dishonesty"
          },
          {
            "sentence": "Detectives are analysing all the forensic ...... (evident) collected from the scene.",
            "answer": "evidence"
          },
          {
            "sentence": "Experts confirmed that the signature on the document was a ...... (forge).",
            "answer": "forgery"
          },
          {
            "sentence": "The court heard that ...... (addict) had driven the defendant to steal in order to fund his habit.",
            "answer": "addiction"
          },
          {
            "sentence": "The ...... (rob) was captured on a security camera outside the shop.",
            "answer": "robbery"
          },
          {
            "sentence": "Anyone can become a ...... (theft) given the right circumstances, according to the psychologist.",
            "answer": "thief"
          },
          {
            "sentence": "The ...... (convict) of the former company director made headlines across the country.",
            "answer": "conviction"
          },
          {
            "sentence": "Critics argue that overcrowded prisons are full of experienced ...... (crime) who share techniques with first-time offenders.",
            "answer": "criminals"
          },
          {
            "sentence": "The question of whether a ...... (murder) should receive a life sentence remains a controversial one.",
            "answer": "murderer"
          }
        ]
      }
    }
  }
}